odoo/addons/purchase_reception_status/README.rst
odoo/addons/purchase_reception_status/__init__.py
odoo/addons/purchase_reception_status/__manifest__.py
odoo/addons/purchase_reception_status/i18n/fr.po
odoo/addons/purchase_reception_status/i18n/purchase_reception_status.pot
odoo/addons/purchase_reception_status/models/__init__.py
odoo/addons/purchase_reception_status/models/purchase_order.py
odoo/addons/purchase_reception_status/readme/CONTRIBUTORS.rst
odoo/addons/purchase_reception_status/readme/DESCRIPTION.rst
odoo/addons/purchase_reception_status/readme/USAGE.rst
odoo/addons/purchase_reception_status/static/description/icon.png
odoo/addons/purchase_reception_status/static/description/index.html
odoo/addons/purchase_reception_status/views/purchase_order.xml
odoo12_addon_purchase_reception_status-12.0.1.0.0.99.dev7.dist-info/METADATA
odoo12_addon_purchase_reception_status-12.0.1.0.0.99.dev7.dist-info/WHEEL
odoo12_addon_purchase_reception_status-12.0.1.0.0.99.dev7.dist-info/top_level.txt
odoo12_addon_purchase_reception_status-12.0.1.0.0.99.dev7.dist-info/RECORD
